{
  "fileName": "Parameters.java",
  "filePath": "common/src/main/java/org/ergoplatform/appkit/Parameters.java",
  "url": "https://github.com/ergoplatform/ergo-appkit/common/src/main/java/org/ergoplatform/appkit/Parameters.java",
  "summary": "The `Parameters` class in the `ergo-appkit` project contains a set of global parameters that are used by the Appkit library. These parameters are constants that are used throughout the project to ensure consistency and to simplify the code.\n\nThe first set of parameters, `MinerRewardDelay_Mainnet` and `MinerRewardDelay_Testnet`, are used to determine the number of blocks a miner must wait before they can spend the block reward. This is a part of the Ergo protocol and cannot be changed.\n\nThe second parameter, `OneErg`, is used to define the conversion rate between Erg and NanoErg. One Erg is equal to 10^9 NanoErg.\n\nThe third parameter, `MinFee`, is the minimum transaction fee in NanoErgs as defined by the Ergo protocol. This value is used to ensure that transactions are processed correctly and that the network is not overloaded with low-value transactions.\n\nThe fourth parameter, `MinChangeValue`, is the minimum value for a change output. If the computed change is less than this value, it is added to the fee and the change output is not added to the transaction. This helps to prevent dust outputs and ensures that transactions are processed efficiently.\n\nThe fifth parameter, `ColdClientMaxBlockCost`, is the maximum block cost for a cold client. This value is used to limit the amount of resources that a cold client can use when processing blocks.\n\nThe final parameter, `ColdClientBlockVersion`, is the activated version for a cold client. This value is used to ensure that the cold client is using the correct version of the Ergo protocol.\n\nOverall, the `Parameters` class provides a set of constants that are used throughout the `ergo-appkit` project to ensure consistency and to simplify the code. These parameters are an important part of the Ergo protocol and are used to ensure that transactions are processed correctly and efficiently.",
  "questions": "1. What is the purpose of this Parameters class?\n- The Parameters class contains global parameters used by the Appkit library.\n\n2. What is the significance of the MinerRewardDelay_Mainnet and MinerRewardDelay_Testnet variables?\n- These variables represent the number of blocks a miner should wait before being able to spend block rewards on the mainnet and testnet, respectively.\n\n3. What is the purpose of the MinChangeValue variable?\n- The MinChangeValue variable represents the minimum value for a change output in a transaction. If the computed change is less than this value, it is added to the fee and the change output is not added to the transaction."
}